{
  "original_filename": "documentation_en-us_unreal-engine_using-distance-field-indirect-shadows-in-unreal-engine_1add5707.html",
  "title": "Using Distance Field Indirect Shadows",
  "slug": "using-distance-field-indirect-shadows-in-unreal-engine",
  "category_path": "Building Virtual Worlds > Lighting the Environment > Mesh Distance Fields",
  "full_navigation_path": [
    "Unreal Engine 5.6 Documentation",
    "Building Virtual Worlds",
    "Lighting the Environment",
    "Mesh Distance Fields",
    "Using Distance Field Indirect Shadows"
  ]
}