{
  "original_filename": "documentation_en-us_unreal-engine_mutable-resource-usage-at-runtime-in-unreal-engine_34564290.html",
  "title": "Resource Usage at Runtime",
  "slug": "mutable-resource-usage-at-runtime-in-unreal-engine",
  "category_path": "Working with Content > Mutable Skeletal Mesh Generation > Mutable Optimizing and Debugging",
  "full_navigation_path": [
    "Unreal Engine 5.6 Documentation",
    "Working with Content",
    "Mutable Skeletal Mesh Generation",
    "Mutable Optimizing and Debugging",
    "Resource Usage at Runtime"
  ]
}