{
  "original_filename": "documentation_en-us_unreal-engine_eqs-node-reference-generators-in-unreal-engine_94250e9f.html",
  "title": "EQS Node Reference: Generators",
  "slug": "eqs-node-reference-generators-in-unreal-engine",
  "category_path": "Gameplay Systems > Artificial Intelligence > Environment Query System > Environment Query System Node Reference",
  "full_navigation_path": [
    "Unreal Engine 5.6 Documentation",
    "Gameplay Systems",
    "Artificial Intelligence",
    "Environment Query System",
    "Environment Query System Node Reference",
    "EQS Node Reference: Generators"
  ]
}