{
  "original_filename": "documentation_en-us_unreal-engine_graphing-in-animation-blueprints-in-unreal-engine_20b349c9.html",
  "title": "Graphing in Animation Blueprints",
  "slug": "graphing-in-animation-blueprints-in-unreal-engine",
  "category_path": "Animating Characters and Objects > Skeletal Mesh Animation System > Animation Blueprints",
  "full_navigation_path": [
    "Unreal Engine 5.6 Documentation",
    "Animating Characters and Objects",
    "Skeletal Mesh Animation System",
    "Animation Blueprints",
    "Graphing in Animation Blueprints"
  ]
}