{
  "original_filename": "documentation_en-us_unreal-engine_online-services-console-commands-in-unreal-engine_c13a7341.html",
  "title": "Online Services Console Commands",
  "slug": "online-services-console-commands-in-unreal-engine",
  "category_path": "Gameplay Systems > Online Subsystems and Services > Online Services > Debugging Online Services Plugin",
  "full_navigation_path": [
    "Unreal Engine 5.6 Documentation",
    "Gameplay Systems",
    "Online Subsystems and Services",
    "Online Services",
    "Debugging Online Services Plugin",
    "Online Services Console Commands"
  ]
}