{
  "original_filename": "documentation_en-us_unreal-engine_lyra-sample-game-interaction-system-in-unreal-engine_481ada4e.html",
  "title": "Lyra Interaction System",
  "slug": "lyra-sample-game-interaction-system-in-unreal-engine",
  "category_path": "Samples and Tutorials > Sample Game Projects > Lyra Sample Game",
  "full_navigation_path": [
    "Unreal Engine 5.6 Documentation",
    "Samples and Tutorials",
    "Sample Game Projects",
    "Lyra Sample Game",
    "Lyra Interaction System"
  ]
}